_streamdm.cpython-37m-darwin.so
ml_rapids/__init__.py
ml_rapids/streamdm.py
ml_rapids/test.py
ml_rapids-0.0.1.7.dist-info/LICENSE
ml_rapids-0.0.1.7.dist-info/METADATA
ml_rapids-0.0.1.7.dist-info/WHEEL
ml_rapids-0.0.1.7.dist-info/top_level.txt
ml_rapids-0.0.1.7.dist-info/RECORD
